gitignore_cli/__init__.py
gitignore_cli/cli.py
gitignore_cli-1.0.4.dist-info/LICENSE
gitignore_cli-1.0.4.dist-info/METADATA
gitignore_cli-1.0.4.dist-info/WHEEL
gitignore_cli-1.0.4.dist-info/entry_points.txt
gitignore_cli-1.0.4.dist-info/top_level.txt
gitignore_cli-1.0.4.dist-info/RECORD
