Metadata-Version: 2.1
Name: gitignore-cli
Version: 1.0.4
Summary: gitignore cli downloader
Home-page: https://github.com/aron-bordin/gitignore-cli
Author: Aron Bordin
Author-email: aron.bordin@gmail.com
License: GPL
Keywords: git gitignore generate download
Platform: UNKNOWN
Classifier: Development Status :: 5 - Production/Stable
Classifier: Intended Audience :: Developers
Classifier: License :: OSI Approved :: GNU General Public License v3 (GPLv3)
Classifier: Operating System :: OS Independent
Classifier: Programming Language :: Python
Classifier: Topic :: Software Development :: Code Generators
Classifier: Topic :: Software Development :: Version Control
Classifier: Topic :: Software Development :: Version Control :: Git
Classifier: Topic :: Utilities
Requires-Dist: PyGithub
Requires-Dist: click
